{
	"class" : {
		 },
	"instance" : {
		"_attributes" : "ThierryGoubier 9/21/2014 17:49:26",
		"_attributes:" : "ThierryGoubier 9/21/2014 17:49:26",
		"acceptVisitor:" : "ThierryGoubier 9/21/2014 17:49:26",
		"addrSpace" : "ThierryGoubier 9/21/2014 17:49:26",
		"addrSpace:" : "ThierryGoubier 9/21/2014 17:49:26",
		"assign" : "ThierryGoubier 9/21/2014 17:49:26",
		"assign:" : "ThierryGoubier 9/21/2014 17:49:26",
		"constant" : "ThierryGoubier 9/21/2014 17:49:26",
		"constant:" : "ThierryGoubier 9/21/2014 17:49:26",
		"internalLinkage" : "ThierryGoubier 9/21/2014 17:49:26",
		"internalLinkage:" : "ThierryGoubier 9/21/2014 17:49:26",
		"otherVariables" : "ThierryGoubier 9/21/2014 17:49:26",
		"thread" : "ThierryGoubier 9/21/2014 17:49:26",
		"thread:" : "ThierryGoubier 9/21/2014 17:49:26",
		"tokenVariables" : "ThierryGoubier 9/21/2014 17:49:26",
		"type" : "ThierryGoubier 9/21/2014 17:49:26",
		"type:" : "ThierryGoubier 9/21/2014 17:49:26",
		"visibility" : "ThierryGoubier 9/21/2014 17:49:26",
		"visibility:" : "ThierryGoubier 9/21/2014 17:49:26" } }
