{
	"class" : {
		"collectionVariableIn:collectionGetter:variableGetter:" : "ThierryGoubier 2/5/2015 17:23:38",
		"new" : "ThierryGoubier 2/5/2015 17:23:38",
		"variableIn:getter:" : "ThierryGoubier 2/5/2015 17:23:38" },
	"instance" : {
		"=" : "ThierryGoubier 2/5/2015 17:23:38",
		"acceptVisitor:" : "ThierryGoubier 2/5/2015 17:23:38",
		"addFirstNode:to:" : "ThierryGoubier 2/5/2015 17:23:38",
		"addFirstNodes:to:" : "ThierryGoubier 2/5/2015 17:23:38",
		"addFirstObject:to:" : "ThierryGoubier 2/5/2015 17:23:38",
		"addFirstObjects:to:" : "ThierryGoubier 2/5/2015 17:23:38",
		"addFirstToken:to:" : "ThierryGoubier 2/5/2015 17:23:38",
		"addFirstTokens:to:" : "ThierryGoubier 2/5/2015 17:23:38",
		"addNode:to:" : "ThierryGoubier 2/5/2015 17:23:38",
		"addNodes:to:" : "ThierryGoubier 2/5/2015 17:23:38",
		"addObject:to:" : "ThierryGoubier 2/5/2015 17:23:38",
		"addObjects:to:" : "ThierryGoubier 2/5/2015 17:23:38",
		"addToken:to:" : "ThierryGoubier 2/5/2015 17:23:38",
		"addTokens:to:" : "ThierryGoubier 2/5/2015 17:23:38",
		"addVariablesFrom:" : "ThierryGoubier 2/5/2015 17:23:38",
		"allGettersDo:" : "ThierryGoubier 2/5/2015 17:23:38",
		"allNodesDo:" : "ThierryGoubier 2/5/2015 17:23:38",
		"allNodesDo:andTokensDo:" : "ThierryGoubier 2/5/2015 17:23:38",
		"allTokens" : "ThierryGoubier 2/5/2015 17:23:38",
		"allTokensInto:" : "ThierryGoubier 2/5/2015 17:23:38",
		"allVariableSelectors" : "ThierryGoubier 2/5/2015 17:23:38",
		"attributeNamed:" : "ThierryGoubier 2/5/2015 17:23:38",
		"attributeNamed:ifAbsent:" : "ThierryGoubier 2/5/2015 17:23:38",
		"attributeNamed:ifAbsentPut:" : "ThierryGoubier 2/5/2015 17:23:38",
		"attributeNamed:put:" : "ThierryGoubier 2/5/2015 17:23:38",
		"attributes" : "ThierryGoubier 2/5/2015 17:23:38",
		"children" : "ThierryGoubier 2/5/2015 17:23:38",
		"comments" : "ThierryGoubier 2/5/2015 17:23:38",
		"comments:" : "ThierryGoubier 2/5/2015 17:23:38",
		"completeSource" : "ThierryGoubier 2/5/2015 17:23:38",
		"completeSource:" : "ThierryGoubier 2/5/2015 17:23:38",
		"compositeNodeVariables" : "ThierryGoubier 2/5/2015 17:23:38",
		"compositeTokenVariables" : "ThierryGoubier 2/5/2015 17:23:38",
		"compositeVariableSelectors" : "ThierryGoubier 2/5/2015 17:23:38",
		"compositeVariables" : "ThierryGoubier 2/5/2015 17:23:38",
		"convertToSetter:" : "ThierryGoubier 2/5/2015 17:23:38",
		"copyInContext:" : "ThierryGoubier 2/5/2015 17:23:38",
		"deleteSource" : "ThierryGoubier 2/5/2015 17:23:38",
		"deleteToken:" : "ThierryGoubier 2/5/2015 17:23:38",
		"filename" : "ThierryGoubier 2/5/2015 17:23:38",
		"filename:" : "ThierryGoubier 2/5/2015 17:23:38",
		"fixParentPointers" : "ThierryGoubier 2/5/2015 17:23:38",
		"hasDescendant:" : "ThierryGoubier 2/5/2015 17:23:38",
		"hash" : "ThierryGoubier 2/5/2015 17:23:38",
		"ignoredCompositeNodeVariables" : "ThierryGoubier 2/5/2015 17:23:38",
		"ignoredCompositeTokenVariables" : "ThierryGoubier 2/5/2015 17:23:38",
		"ignoredNodeVariables" : "ThierryGoubier 2/5/2015 17:23:38",
		"ignoredOtherVariables" : "ThierryGoubier 2/5/2015 17:23:38",
		"ignoredTokenVariables" : "ThierryGoubier 2/5/2015 17:23:38",
		"insertSourceAfter:" : "ThierryGoubier 2/5/2015 17:23:38",
		"insertSourceBefore:" : "ThierryGoubier 2/5/2015 17:23:38",
		"insertSourceBefore:andAfter:" : "ThierryGoubier 2/5/2015 17:23:38",
		"isDescendantFrom:" : "ThierryGoubier 2/5/2015 17:23:38",
		"isListMatch" : "ThierryGoubier 2/5/2015 17:23:38",
		"lookupNode:" : "ThierryGoubier 2/5/2015 17:23:38",
		"match:inContext:" : "ThierryGoubier 2/5/2015 17:23:38",
		"matchCollection:index:to:index:inContext:" : "ThierryGoubier 2/5/2015 17:23:38",
		"matchCollection:to:inContext:" : "ThierryGoubier 2/5/2015 17:23:38",
		"nodeOfType:" : "ThierryGoubier 2/5/2015 17:23:38",
		"nodeVariables" : "ThierryGoubier 2/5/2015 17:23:38",
		"nodesDo:" : "ThierryGoubier 2/5/2015 17:23:38",
		"nodesDo:andTokensDo:" : "ThierryGoubier 2/5/2015 17:23:38",
		"otherVariables" : "ThierryGoubier 2/5/2015 17:23:38",
		"parent" : "ThierryGoubier 2/5/2015 17:23:38",
		"parent:" : "ThierryGoubier 2/5/2015 17:23:38",
		"parentOfType:" : "ThierryGoubier 2/5/2015 17:23:38",
		"pluralVariablesMap" : "ThierryGoubier 2/5/2015 17:23:38",
		"postCopy" : "ThierryGoubier 2/5/2015 17:23:38",
		"removeAttributeNamed:" : "ThierryGoubier 2/5/2015 17:23:38",
		"replace:with:" : "ThierryGoubier 8/18/2015 18:03",
		"replaceToken:withSource:" : "ThierryGoubier 2/5/2015 17:23:38",
		"replaceWith:" : "ThierryGoubier 2/5/2015 17:23:38",
		"replaceWithSource:" : "ThierryGoubier 2/5/2015 17:23:38",
		"safePerform:" : "ThierryGoubier 2/5/2015 17:23:38",
		"setParents:to:" : "ThierryGoubier 2/5/2015 17:23:38",
		"singularVariableSelectors" : "ThierryGoubier 2/5/2015 17:23:38",
		"singularVariables" : "ThierryGoubier 2/5/2015 17:23:38",
		"sortedChildren" : "ThierryGoubier 2/5/2015 17:23:38",
		"source" : "ThierryGoubier 2/5/2015 17:23:38",
		"startPosition" : "ThierryGoubier 2/5/2015 17:23:38",
		"stopPosition" : "ThierryGoubier 2/5/2015 17:23:38",
		"tokenVariables" : "ThierryGoubier 2/5/2015 17:23:38",
		"topParent" : "ThierryGoubier 2/5/2015 17:23:38",
		"variableSelectors" : "ThierryGoubier 2/5/2015 17:23:38" } }
