{
	"class" : {
		 },
	"instance" : {
		"acceptVisitor:" : "ThierryGoubier 2/24/2015 14:38:21",
		"ignoredTokenVariables" : "ThierryGoubier 2/24/2015 14:38:21",
		"left" : "ThierryGoubier 2/24/2015 14:38:21",
		"left:" : "ThierryGoubier 2/24/2015 14:38:21",
		"nodeVariables" : "ThierryGoubier 2/24/2015 14:38:21",
		"right" : "ThierryGoubier 2/24/2015 14:38:21",
		"right:" : "ThierryGoubier 2/24/2015 14:38:21",
		"variable" : "ThierryGoubier 2/24/2015 14:38:21",
		"variable:" : "ThierryGoubier 2/24/2015 14:38:21" } }
