{
	"class" : {
		"initializeKeywordMap" : "JohnBrant 6/24/2016 10:40:06" },
	"instance" : {
		"GREATER_THANId" : "JohnBrant 6/24/2016 10:40:06",
		"SIGNED_RIGHT_SHIFTId" : "JohnBrant 6/24/2016 10:40:06",
		"UNSIGNED_RIGHT_SHIFTId" : "JohnBrant 6/24/2016 10:40:06",
		"emptySymbolTokenId" : "JohnBrant 6/24/2016 10:40:06",
		"errorTokenId" : "JohnBrant 6/24/2016 10:40:06",
		"scan1" : "JohnBrant 6/24/2016 10:40:06",
		"scan10" : "JohnBrant 6/24/2016 10:40:06",
		"scan2" : "JohnBrant 6/24/2016 10:40:06",
		"scan3" : "JohnBrant 6/24/2016 10:40:06",
		"scan4" : "JohnBrant 6/24/2016 10:40:06",
		"scan5" : "JohnBrant 6/24/2016 10:40:06",
		"scan6" : "JohnBrant 6/24/2016 10:40:06",
		"scan7" : "JohnBrant 6/24/2016 10:40:06",
		"scan8" : "JohnBrant 6/24/2016 10:40:06",
		"scan9" : "JohnBrant 6/24/2016 10:40:06",
		"scanForToken" : "JohnBrant 6/24/2016 10:40:06",
		"scanForTokenX1" : "JohnBrant 6/24/2016 10:40:06",
		"scanForTokenX10" : "JohnBrant 6/24/2016 10:40:06",
		"scanForTokenX11" : "JohnBrant 6/24/2016 10:40:06",
		"scanForTokenX12" : "JohnBrant 6/24/2016 10:40:06",
		"scanForTokenX13" : "JohnBrant 6/24/2016 10:40:06",
		"scanForTokenX14" : "JohnBrant 6/24/2016 10:40:06",
		"scanForTokenX15" : "JohnBrant 6/24/2016 10:40:06",
		"scanForTokenX16" : "JohnBrant 6/24/2016 10:40:06",
		"scanForTokenX17" : "JohnBrant 6/24/2016 10:40:06",
		"scanForTokenX18" : "JohnBrant 6/24/2016 10:40:06",
		"scanForTokenX19" : "JohnBrant 6/24/2016 10:40:06",
		"scanForTokenX2" : "JohnBrant 6/24/2016 10:40:06",
		"scanForTokenX3" : "JohnBrant 6/24/2016 10:40:06",
		"scanForTokenX4" : "JohnBrant 6/24/2016 10:40:06",
		"scanForTokenX5" : "JohnBrant 6/24/2016 10:40:06",
		"scanForTokenX6" : "JohnBrant 6/24/2016 10:40:06",
		"scanForTokenX7" : "JohnBrant 6/24/2016 10:40:06",
		"scanForTokenX8" : "JohnBrant 6/24/2016 10:40:06",
		"scanForTokenX9" : "JohnBrant 6/24/2016 10:40:06",
		"tokenActions" : "JohnBrant 6/24/2016 10:40:06" } }
