{
	"class" : {
		"initialize" : "ThierryGoubier 9/18/2014 17:03:41",
		"new" : "ThierryGoubier 9/18/2014 17:03:41" },
	"instance" : {
		"<=" : "ThierryGoubier 9/18/2014 17:03:41",
		"=" : "ThierryGoubier 9/18/2014 17:03:41",
		"action" : "ThierryGoubier 9/18/2014 17:03:41",
		"action:" : "ThierryGoubier 9/18/2014 17:03:41",
		"actionForSpecificRegularExpression:" : "ThierryGoubier 9/18/2014 17:03:41",
		"addActions:" : "ThierryGoubier 9/18/2014 17:03:41",
		"addEdgeTo:" : "ThierryGoubier 9/18/2014 17:03:41",
		"addEdgeTo:onCharacters:" : "ThierryGoubier 9/18/2014 17:03:41",
		"addEdgeTo:onStates:" : "ThierryGoubier 9/18/2014 17:03:41",
		"allStates" : "ThierryGoubier 9/18/2014 17:03:41",
		"allStatesInto:" : "ThierryGoubier 9/18/2014 17:03:41",
		"allTransitionsWith:" : "ThierryGoubier 9/18/2014 17:03:41",
		"allTransitionsWith:visited:" : "ThierryGoubier 9/18/2014 17:03:41",
		"asDFA" : "ThierryGoubier 9/18/2014 17:03:41",
		"asDOTstring" : "ThierryGoubier 9/18/2014 17:03:41",
		"asNFAWithoutEpsilonTransitions" : "ThierryGoubier 9/18/2014 17:03:41",
		"getId" : "ThierryGoubier 9/18/2014 17:03:41",
		"groupedTransitions" : "ThierryGoubier 9/18/2014 17:03:41",
		"hasSimpleLoop" : "ThierryGoubier 9/18/2014 17:03:41",
		"hash" : "ThierryGoubier 9/18/2014 17:03:41",
		"id" : "ThierryGoubier 9/18/2014 17:03:41",
		"initialize" : "ThierryGoubier 9/18/2014 17:03:41",
		"isTerminalNode" : "ThierryGoubier 9/18/2014 17:03:41",
		"maxSubNodesInMethod" : "ThierryGoubier 9/18/2014 17:03:41",
		"mergeTransitions" : "ThierryGoubier 9/18/2014 17:03:41",
		"mergeWith:" : "ThierryGoubier 9/18/2014 17:03:41",
		"orderNodes" : "ThierryGoubier 9/18/2014 17:03:41",
		"orderNodesWithId:map:" : "ThierryGoubier 9/18/2014 17:03:41",
		"printOn:" : "ThierryGoubier 9/18/2014 17:03:41",
		"removeDuplicateNodes" : "ThierryGoubier 9/18/2014 17:03:41",
		"shallowCopy" : "ThierryGoubier 9/18/2014 17:03:41",
		"simulate:" : "ThierryGoubier 9/18/2014 17:03:41",
		"sortedTransitions" : "ThierryGoubier 9/18/2014 17:03:41",
		"startingNodeWithoutUnnecessaryDefaultTransition" : "ThierryGoubier 9/18/2014 17:03:41",
		"transitions" : "ThierryGoubier 9/18/2014 17:03:41",
		"transitions:" : "ThierryGoubier 9/18/2014 17:03:41" } }
