{
	"class" : {
		"initialize" : "JohnBrant 6/24/2016 12:26:52",
		"new" : "JohnBrant 6/24/2016 12:26:52" },
	"instance" : {
		"<=" : "JohnBrant 6/24/2016 12:26:52",
		"=" : "JohnBrant 6/24/2016 12:26:52",
		"action" : "JohnBrant 6/24/2016 12:26:52",
		"action:" : "JohnBrant 6/24/2016 12:26:52",
		"actionForSpecificRegularExpression:" : "JohnBrant 6/24/2016 12:26:52",
		"addActions:" : "JohnBrant 6/24/2016 12:26:52",
		"addEdgeTo:" : "JohnBrant 6/24/2016 12:26:52",
		"addEdgeTo:onCharacters:" : "JohnBrant 6/24/2016 12:26:52",
		"addEdgeTo:onStates:" : "JohnBrant 6/24/2016 12:26:52",
		"allStates" : "JohnBrant 6/24/2016 12:26:52",
		"allStatesInto:" : "JohnBrant 6/24/2016 12:26:52",
		"asDFA" : "JohnBrant 6/24/2016 12:26:52",
		"asDOTstring" : "JohnBrant 6/24/2016 12:26:52",
		"asNFAWithoutEpsilonTransitions" : "JohnBrant 6/24/2016 12:26:52",
		"codeSizeEstimate:" : "JohnBrant 6/24/2016 12:26:52",
		"getId" : "JohnBrant 6/24/2016 12:26:52",
		"groupedTransitions" : "JohnBrant 6/24/2016 12:26:52",
		"hasSimpleLoop" : "JohnBrant 6/24/2016 12:26:52",
		"hash" : "JohnBrant 6/24/2016 12:26:52",
		"id" : "JohnBrant 6/24/2016 12:26:52",
		"initialize" : "JohnBrant 6/24/2016 12:26:52",
		"isTerminalNode" : "JohnBrant 6/24/2016 12:26:52",
		"mergeTransitions" : "JohnBrant 6/24/2016 12:26:52",
		"mergeWith:" : "JohnBrant 6/24/2016 12:26:52",
		"orderNodes" : "JohnBrant 6/24/2016 12:26:52",
		"orderNodesWithId:map:" : "JohnBrant 6/24/2016 12:26:52",
		"printOn:" : "JohnBrant 6/24/2016 12:26:52",
		"removeDuplicateNodes" : "JohnBrant 6/24/2016 12:26:52",
		"shallowCopy" : "JohnBrant 6/24/2016 12:26:52",
		"simulate:" : "JohnBrant 6/24/2016 12:26:52",
		"sortedTransitions" : "JohnBrant 6/24/2016 12:26:52",
		"startingNodeWithoutUnnecessaryDefaultTransition" : "JohnBrant 6/24/2016 12:26:52",
		"transitions" : "JohnBrant 6/24/2016 12:26:52",
		"transitions:" : "JohnBrant 6/24/2016 12:26:52" } }
