{
	"class" : {
		"new" : "ThierryGoubier 8/26/2014 18:36:12" },
	"instance" : {
		"addSubclass:" : "ThierryGoubier 8/26/2014 18:36:12",
		"beRoot" : "ThierryGoubier 8/26/2014 18:36:12",
		"codeGenerator" : "ThierryGoubier 8/26/2014 18:36:12",
		"commonSuperclass:" : "ThierryGoubier 8/26/2014 18:36:12",
		"compileMethodsAndVariables" : "ThierryGoubier 8/26/2014 18:36:12",
		"fullName" : "ThierryGoubier 8/26/2014 18:36:12",
		"grammar:" : "ThierryGoubier 8/26/2014 18:36:12",
		"hierarchyCount" : "ThierryGoubier 8/26/2014 18:36:12",
		"hierarchyIncludes:" : "ThierryGoubier 8/26/2014 18:36:12",
		"initialize" : "ThierryGoubier 8/26/2014 18:36:12",
		"isRoot" : "ThierryGoubier 8/26/2014 18:36:12",
		"isSortedBefore:" : "ThierryGoubier 8/26/2014 18:36:12",
		"modelClass" : "ThierryGoubier 8/26/2014 18:36:12",
		"modelClass:" : "ThierryGoubier 8/26/2014 18:36:12",
		"name" : "ThierryGoubier 8/26/2014 18:36:12",
		"name:" : "ThierryGoubier 8/26/2014 18:36:12",
		"printOn:" : "ThierryGoubier 8/26/2014 18:36:12",
		"removeSubclass:" : "ThierryGoubier 8/26/2014 18:36:12",
		"rootClassName" : "ThierryGoubier 8/26/2014 18:36:12",
		"subclasses" : "ThierryGoubier 8/26/2014 18:36:12",
		"superclass" : "ThierryGoubier 8/26/2014 18:36:12",
		"superclass:" : "ThierryGoubier 8/26/2014 18:36:12",
		"superclassName" : "ThierryGoubier 8/26/2014 18:36:12",
		"temporaryNameFor:" : "ThierryGoubier 8/26/2014 18:36:12",
		"temporaryVariableName" : "ThierryGoubier 8/26/2014 18:36:12",
		"withAllSubclasses" : "ThierryGoubier 8/26/2014 18:36:12" } }
