{
	"class" : {
		 },
	"instance" : {
		"acceptVisitor:" : "ThierryGoubier 9/11/2014 13:40",
		"anothers" : "ThierryGoubier 9/11/2014 13:39",
		"anothers:" : "ThierryGoubier 9/11/2014 13:39",
		"asTokens" : "ThierryGoubier 9/11/2014 13:39",
		"asTokens:" : "ThierryGoubier 9/11/2014 13:39",
		"colonTokens" : "ThierryGoubier 9/11/2014 13:39",
		"colonTokens:" : "ThierryGoubier 9/11/2014 13:39",
		"commaTokens" : "ThierryGoubier 9/11/2014 13:39",
		"commaTokens:" : "ThierryGoubier 9/11/2014 13:39",
		"compositeNodeVariables" : "ThierryGoubier 9/11/2014 17:02",
		"compositeTokenVariables" : "ThierryGoubier 9/11/2014 13:39",
		"dEDENTTokens" : "ThierryGoubier 9/11/2014 13:39",
		"dEDENTTokens:" : "ThierryGoubier 9/11/2014 13:39",
		"except2s" : "ThierryGoubier 9/11/2014 13:39",
		"except2s:" : "ThierryGoubier 9/11/2014 13:39",
		"exceptTokens" : "ThierryGoubier 9/11/2014 13:39",
		"exceptTokens:" : "ThierryGoubier 9/11/2014 13:39",
		"excepts" : "ThierryGoubier 9/11/2014 13:39",
		"excepts:" : "ThierryGoubier 9/11/2014 13:39",
		"iNDENTTokens" : "ThierryGoubier 9/11/2014 13:39",
		"iNDENTTokens:" : "ThierryGoubier 9/11/2014 13:39",
		"initialize" : "ThierryGoubier 9/11/2014 17:02",
		"nEWLINETokens" : "ThierryGoubier 9/11/2014 13:39",
		"nEWLINETokens:" : "ThierryGoubier 9/11/2014 13:39",
		"pluralVariablesMap" : "ThierryGoubier 9/11/2014 17:02",
		"suites" : "ThierryGoubier 9/11/2014 17:02",
		"suites:" : "ThierryGoubier 9/11/2014 17:02" } }
