{
	"class" : {
		"basedOn:" : "ThierryGoubier 4/27/2014 17:57:11",
		"new" : "ThierryGoubier 4/27/2014 17:57:11" },
	"instance" : {
		"add:" : "ThierryGoubier 4/27/2014 17:57:11",
		"addAll:" : "ThierryGoubier 4/27/2014 17:57:11",
		"addComponent:" : "ThierryGoubier 4/27/2014 17:57:11",
		"addComponentsFrom:" : "ThierryGoubier 4/27/2014 17:57:11",
		"allSatisfy:" : "ThierryGoubier 4/27/2014 17:57:11",
		"baseOn:" : "ThierryGoubier 4/27/2014 17:57:11",
		"components" : "ThierryGoubier 4/27/2014 17:57:11",
		"getDependents" : "ThierryGoubier 4/27/2014 17:57:11",
		"includes:" : "ThierryGoubier 4/27/2014 17:57:11",
		"initialize" : "ThierryGoubier 4/27/2014 17:57:11",
		"mergeWith:" : "ThierryGoubier 4/27/2014 17:57:11",
		"printOn:" : "ThierryGoubier 4/27/2014 17:57:11",
		"setDependents:" : "ThierryGoubier 4/27/2014 17:57:11",
		"size" : "ThierryGoubier 4/27/2014 17:57:11",
		"symbols" : "ThierryGoubier 4/27/2014 17:57:11",
		"update:" : "ThierryGoubier 4/27/2014 17:57:11",
		"update:with:from:" : "ThierryGoubier 4/27/2014 17:57:11" } }
