{
	"class" : {
		"initializeKeywordMap" : "ThierryGoubier 2/11/2014 16:03" },
	"instance" : {
		"binarySymbolId" : "ThierryGoubier 2/11/2014 16:03",
		"emptySymbolTokenId" : "ThierryGoubier 2/11/2014 16:03",
		"errorTokenId" : "ThierryGoubier 2/11/2014 16:03",
		"nameId" : "ThierryGoubier 2/11/2014 16:03",
		"negativeNumber" : "ThierryGoubier 1/27/2014 16:02:55",
		"negativeNumberId" : "ThierryGoubier 2/11/2014 16:03",
		"number" : "ThierryGoubier 1/27/2014 16:02:55",
		"numberId" : "ThierryGoubier 2/11/2014 16:03",
		"scan1" : "ThierryGoubier 2/11/2014 16:03",
		"scan2" : "ThierryGoubier 2/11/2014 16:03",
		"scan3" : "ThierryGoubier 2/11/2014 16:03",
		"scan4" : "ThierryGoubier 2/11/2014 16:03",
		"scan5" : "ThierryGoubier 2/11/2014 16:03",
		"scanForToken" : "ThierryGoubier 2/11/2014 16:03",
		"scanNumber:" : "ThierryGoubier 1/27/2014 16:02:55",
		"tokenActions" : "ThierryGoubier 2/11/2014 16:03",
		"variableAssignment" : "ThierryGoubier 1/27/2014 16:02:55" } }
