{
	"instance" : {
		"hasVariableNamed:" : "ThierryGoubier 3/27/2017 22:53:01",
		"firstTerminals" : "ThierryGoubier 3/27/2017 22:53:01",
		"modelType:" : "ThierryGoubier 3/27/2017 22:53:01",
		"returnsSingleVariable" : "ThierryGoubier 3/27/2017 22:53:01",
		"variableDefinitions" : "ThierryGoubier 3/27/2017 22:53:01",
		"modelTypesForVariable:seen:" : "ThierryGoubier 3/27/2017 22:53:01",
		"grammar" : "ThierryGoubier 3/27/2017 22:53:01",
		"model" : "ThierryGoubier 3/27/2017 22:53:01",
		"modelTypes" : "ThierryGoubier 3/27/2017 22:53:01",
		"annotateTokenVariables:" : "ThierryGoubier 3/27/2017 22:53:01",
		"grammar:" : "ThierryGoubier 3/27/2017 22:53:01",
		"nodeType:" : "ThierryGoubier 3/27/2017 22:53:01",
		"indexOfVariable:" : "ThierryGoubier 3/27/2017 22:53:01",
		"nodeType" : "ThierryGoubier 3/27/2017 22:53:01",
		"isCollection:" : "ThierryGoubier 3/27/2017 22:53:01",
		"modelTypesForVariable:" : "ThierryGoubier 3/27/2017 22:53:01",
		"isNode" : "ThierryGoubier 3/27/2017 22:53:01",
		"basicModelTypesForVariable:into:seen:" : "ThierryGoubier 3/27/2017 22:53:01",
		"isSubtypeOf:" : "ThierryGoubier 3/27/2017 22:53:01",
		"returnsVariableCollection" : "ThierryGoubier 3/27/2017 22:53:01",
		"collectionVariableDefinitions" : "ThierryGoubier 3/27/2017 22:53:01",
		"computeVariableDefinitions" : "ThierryGoubier 3/27/2017 22:53:01",
		"modelType" : "ThierryGoubier 3/27/2017 22:53:01",
		"modelTypes:" : "ThierryGoubier 3/27/2017 22:53:01"
	},
	"class" : {
		"new" : "ThierryGoubier 3/27/2017 22:53:01"
	}
}