{
	"class" : {
		"compileForGrammar:" : "ThierryGoubier 2/4/2014 15:06:58" },
	"instance" : {
		"calculateReduceActions" : "ThierryGoubier 2/4/2014 15:06:58",
		"calculateSymbolVariables" : "ThierryGoubier 2/4/2014 15:06:58",
		"calculateSymbolVariablesFor:" : "ThierryGoubier 2/4/2014 15:06:58",
		"calculateVariables" : "ThierryGoubier 2/4/2014 15:06:58",
		"codeGenerator" : "ThierryGoubier 2/4/2014 15:06:58",
		"compileMethodsAndVariables" : "ThierryGoubier 2/4/2014 15:06:58",
		"compileNodeClasses" : "ThierryGoubier 2/4/2014 15:06:58",
		"compileTypes" : "ThierryGoubier 2/4/2014 15:06:58",
		"compileVisitor" : "ThierryGoubier 2/4/2014 15:06:58",
		"defineNodeClasses" : "ThierryGoubier 2/4/2014 15:06:58",
		"grammar:" : "ThierryGoubier 2/4/2014 15:06:58",
		"hasVariables:seen:" : "ThierryGoubier 2/4/2014 15:06:58",
		"sortedClasses" : "ThierryGoubier 2/4/2014 15:06:58" } }
