{
	"class" : {
		 },
	"instance" : {
		"acceptVisitor:" : "ThierryGoubier 4/19/2014 10:27:56",
		"baseExpression" : "ThierryGoubier 4/19/2014 10:27:56",
		"baseExpression:" : "ThierryGoubier 4/19/2014 10:27:56",
		"commaTokens" : "ThierryGoubier 4/19/2014 10:27:56",
		"commaTokens:" : "ThierryGoubier 4/19/2014 10:27:56",
		"compositeNodeVariables" : "ThierryGoubier 4/19/2014 10:27:56",
		"expressions" : "ThierryGoubier 4/19/2014 10:27:56",
		"expressions:" : "ThierryGoubier 4/19/2014 10:27:56",
		"ignoredCompositeTokenVariables" : "ThierryGoubier 4/19/2014 10:27:56",
		"initialize" : "ThierryGoubier 4/19/2014 10:27:56",
		"leftBracketToken" : "ThierryGoubier 4/19/2014 10:27:56",
		"leftBracketToken:" : "ThierryGoubier 4/19/2014 10:27:56",
		"nodeVariables" : "ThierryGoubier 4/19/2014 10:27:56",
		"rightBracketToken" : "ThierryGoubier 4/19/2014 10:27:56",
		"rightBracketToken:" : "ThierryGoubier 4/19/2014 10:27:56",
		"tokenVariables" : "ThierryGoubier 4/19/2014 10:27:56" } }
