{
	"class" : {
		"to:on:" : "ThierryGoubier 10/17/2014 17:15:44" },
	"instance" : {
		"<=" : "ThierryGoubier 10/17/2014 17:15:44",
		"=" : "ThierryGoubier 10/17/2014 17:15:44",
		"canMergeWith:" : "ThierryGoubier 10/17/2014 17:15:44",
		"dispatchTo:seen:" : "ThierryGoubier 10/17/2014 17:15:44",
		"edgeFrequencyUsingTable:" : "ThierryGoubier 10/17/2014 17:15:44",
		"edgeLabel" : "ThierryGoubier 10/17/2014 17:15:44",
		"hash" : "ThierryGoubier 10/17/2014 17:15:44",
		"includes:" : "ThierryGoubier 10/17/2014 17:15:44",
		"isCharacterTransition" : "ThierryGoubier 10/17/2014 17:15:44",
		"isEmpty" : "ThierryGoubier 10/17/2014 17:15:44",
		"isEpsilonTransition" : "ThierryGoubier 10/17/2014 17:15:44",
		"mergeWith:" : "ThierryGoubier 10/17/2014 17:15:44",
		"printOn:" : "ThierryGoubier 10/17/2014 17:15:44",
		"remove:" : "ThierryGoubier 10/17/2014 17:15:44",
		"setClass" : "ThierryGoubier 10/17/2014 17:15:44",
		"to" : "ThierryGoubier 10/17/2014 17:15:44",
		"to:" : "ThierryGoubier 10/17/2014 17:15:44",
		"to:on:" : "ThierryGoubier 10/17/2014 17:15:44",
		"transitionObjects" : "ThierryGoubier 10/17/2014 17:15:44" } }
