{
	"instance" : {
		"convertToRemoved" : "ThierryGoubier 9/23/2016 19:27:16",
		"previous:" : "ThierryGoubier 9/23/2016 19:27:16",
		"startIndex" : "ThierryGoubier 9/23/2016 19:27:16",
		"annotations" : "ThierryGoubier 9/23/2016 19:27:16",
		"start:" : "ThierryGoubier 9/23/2016 19:27:16",
		"stopIndex" : "ThierryGoubier 9/23/2016 19:27:16",
		"nextPutOn:" : "ThierryGoubier 9/23/2016 19:27:16",
		"isRemoved:" : "ThierryGoubier 9/23/2016 19:27:16",
		"previous" : "ThierryGoubier 9/23/2016 19:27:16",
		"beSentinel" : "ThierryGoubier 9/23/2016 19:27:16",
		"next:" : "ThierryGoubier 9/23/2016 19:27:16",
		"next" : "ThierryGoubier 9/23/2016 19:27:16",
		"stop" : "ThierryGoubier 9/23/2016 19:27:16",
		"insertAfter:" : "ThierryGoubier 9/23/2016 19:27:16",
		"addAllAnnotations:" : "ThierryGoubier 9/23/2016 19:27:16",
		"size" : "ThierryGoubier 9/23/2016 19:27:16",
		"do:" : "ThierryGoubier 9/23/2016 19:27:16",
		"asString" : "ThierryGoubier 9/23/2016 19:27:16",
		"stop:" : "ThierryGoubier 9/23/2016 19:27:16",
		"string" : "ThierryGoubier 9/23/2016 19:27:16",
		"isSentinel" : "ThierryGoubier 9/23/2016 19:27:16",
		"isRemoved" : "ThierryGoubier 9/23/2016 19:27:16",
		"string:" : "ThierryGoubier 9/23/2016 19:27:16",
		"containsIndex:" : "ThierryGoubier 9/23/2016 19:27:16",
		"splitAt:" : "ThierryGoubier 9/23/2016 19:27:16",
		"id:" : "ThierryGoubier 9/23/2016 19:27:16",
		"removedString" : "ThierryGoubier 9/23/2016 19:27:16",
		"canBeMergedWith:" : "ThierryGoubier 9/23/2016 19:27:16",
		"id" : "ThierryGoubier 9/23/2016 19:27:16",
		"annotationsTo:" : "ThierryGoubier 9/23/2016 19:27:16",
		"printOn:" : "ThierryGoubier 9/23/2016 19:27:16",
		"isEmpty" : "ThierryGoubier 9/23/2016 19:27:16",
		"removed" : "ThierryGoubier 9/23/2016 19:27:16",
		"start" : "ThierryGoubier 9/23/2016 19:27:16"
	},
	"class" : {
		"from:to:string:" : "ThierryGoubier 9/23/2016 19:27:16"
	}
}