{
	"class" : {
		"new" : "ThierryGoubier 4/27/2014 17:57:11" },
	"instance" : {
		"addExcludeState:" : "ThierryGoubier 4/27/2014 17:57:11",
		"addState:" : "ThierryGoubier 4/27/2014 17:57:11",
		"addToken:withName:" : "ThierryGoubier 4/27/2014 17:57:11",
		"defaultState" : "ThierryGoubier 4/27/2014 17:57:11",
		"includesTokenNamed:" : "ThierryGoubier 4/27/2014 17:57:11",
		"initialize" : "ThierryGoubier 4/27/2014 17:57:11",
		"isExcludeState:" : "ThierryGoubier 4/27/2014 17:57:11",
		"nonExcludeStates" : "ThierryGoubier 4/27/2014 17:57:11",
		"states" : "ThierryGoubier 4/27/2014 17:57:11",
		"tokenNamed:" : "ThierryGoubier 4/27/2014 17:57:11",
		"tokenNamed:ifAbsentPut:" : "ThierryGoubier 4/27/2014 17:57:11",
		"tokens" : "ThierryGoubier 4/27/2014 17:57:11" } }
