{
	"class" : {
		"needsLineNumbers" : "ThierryGoubier 2/4/2014 15:06:58" },
	"instance" : {
		"canParse:" : "ThierryGoubier 2/4/2014 15:06:58",
		"canParseSmalltalk:" : "ThierryGoubier 2/4/2014 15:06:58",
		"classLeftId" : "ThierryGoubier 2/4/2014 15:06:58",
		"classRightId" : "ThierryGoubier 2/4/2014 15:06:58",
		"code" : "ThierryGoubier 2/4/2014 15:06:58",
		"codeId" : "ThierryGoubier 2/4/2014 15:06:58",
		"directiveId" : "ThierryGoubier 2/4/2014 15:06:58",
		"emptySymbolTokenId" : "ThierryGoubier 2/4/2014 15:06:58",
		"errorTokenId" : "ThierryGoubier 2/4/2014 15:06:58",
		"initialize" : "ThierryGoubier 2/4/2014 15:06:58",
		"keywordId" : "ThierryGoubier 2/4/2014 15:06:58",
		"parseSourceSelector:" : "ThierryGoubier 2/4/2014 15:06:58",
		"productionId" : "ThierryGoubier 2/4/2014 15:06:58",
		"scan1" : "ThierryGoubier 2/4/2014 15:06:58",
		"scan10" : "ThierryGoubier 2/4/2014 15:06:58",
		"scan11" : "ThierryGoubier 2/4/2014 15:06:58",
		"scan12" : "ThierryGoubier 2/4/2014 15:06:58",
		"scan13" : "ThierryGoubier 2/4/2014 15:06:58",
		"scan14" : "ThierryGoubier 2/4/2014 15:06:58",
		"scan15" : "ThierryGoubier 2/4/2014 15:06:58",
		"scan16" : "ThierryGoubier 2/4/2014 15:06:58",
		"scan17" : "ThierryGoubier 2/4/2014 15:06:58",
		"scan18" : "ThierryGoubier 2/4/2014 15:06:58",
		"scan19" : "ThierryGoubier 2/4/2014 15:06:58",
		"scan2" : "ThierryGoubier 2/4/2014 15:06:58",
		"scan20" : "ThierryGoubier 2/4/2014 15:06:58",
		"scan21" : "ThierryGoubier 2/4/2014 15:06:58",
		"scan22" : "ThierryGoubier 2/4/2014 15:06:58",
		"scan23" : "ThierryGoubier 2/4/2014 15:06:58",
		"scan24" : "ThierryGoubier 2/4/2014 15:06:58",
		"scan25" : "ThierryGoubier 2/4/2014 15:06:58",
		"scan26" : "ThierryGoubier 2/4/2014 15:06:58",
		"scan27" : "ThierryGoubier 2/4/2014 15:06:58",
		"scan28" : "ThierryGoubier 2/4/2014 15:06:58",
		"scan3" : "ThierryGoubier 2/4/2014 15:06:58",
		"scan4" : "ThierryGoubier 2/4/2014 15:06:58",
		"scan5" : "ThierryGoubier 2/4/2014 15:06:58",
		"scan6" : "ThierryGoubier 2/4/2014 15:06:58",
		"scan7" : "ThierryGoubier 2/4/2014 15:06:58",
		"scan8" : "ThierryGoubier 2/4/2014 15:06:58",
		"scan9" : "ThierryGoubier 2/4/2014 15:06:58",
		"scanForToken" : "ThierryGoubier 2/4/2014 15:06:58",
		"semicolonId" : "ThierryGoubier 2/4/2014 15:06:58",
		"symbolnameId" : "ThierryGoubier 2/4/2014 15:06:58",
		"tokenActions" : "ThierryGoubier 2/4/2014 15:06:58",
		"tokennameId" : "ThierryGoubier 2/4/2014 15:06:58",
		"variablenameId" : "ThierryGoubier 2/4/2014 15:06:58" } }
