{
	"class" : {
		 },
	"instance" : {
		"acceptVisitor:" : "ThierryGoubier 9/21/2014 17:49:26",
		"assign" : "ThierryGoubier 9/21/2014 17:49:26",
		"assign:" : "ThierryGoubier 9/21/2014 17:49:26",
		"otherVariables" : "ThierryGoubier 9/21/2014 17:49:26",
		"tokenVariables" : "ThierryGoubier 9/21/2014 17:49:26",
		"typeToken" : "ThierryGoubier 9/21/2014 17:49:26",
		"typeToken:" : "ThierryGoubier 9/21/2014 17:49:26",
		"types" : "ThierryGoubier 9/21/2014 17:49:26",
		"types:" : "ThierryGoubier 9/21/2014 17:49:26" } }
